zephyr_results_publisher/__init__.py
zephyr_results_publisher/behave_to_cucumber_converter.py
zephyr_results_publisher/file_util.py
zephyr_results_publisher/helper.py
zephyr_results_publisher/publisher.py
zephyr_results_publisher/model/cucumber_report_schema.json
zephyr_results_publisher-0.2.0.dist-info/LICENSE.txt
zephyr_results_publisher-0.2.0.dist-info/METADATA
zephyr_results_publisher-0.2.0.dist-info/WHEEL
zephyr_results_publisher-0.2.0.dist-info/top_level.txt
zephyr_results_publisher-0.2.0.dist-info/RECORD
