Metadata-Version: 2.1
Name: zephyr-results-publisher
Version: 0.2.0
Summary: Automation results publisher to Zephyr Scale Cloud
Author-email: Vitalii Rymar <vitalii.stas.rymar@gmail.com>
License: MIT
Project-URL: homepage, https://github.com/Vitalizzzer/zephyr-results-publisher
Project-URL: repository, https://github.com/Vitalizzzer/zephyr-results-publisher
Keywords: zephyr,scale,smartbear,jira,api,automation,report
Classifier: Operating System :: Microsoft :: Windows
Classifier: Operating System :: MacOS
Classifier: Operating System :: Unix
Classifier: License :: OSI Approved :: MIT License
Classifier: Programming Language :: Python :: 3
License-File: LICENSE.txt
Requires-Dist: requests (>=2.27.1)
Requires-Dist: requests-toolbelt (>=0.9.1)
Requires-Dist: jsonschema (>=4.5.1)
